examples/OptimizeCNN.py
examples/OptimizeCNNExample.py
examples/OptimizeMNistExample.py
examples/PlantDiseaseDetectionCNN.py
examples/__init__.py
pykopt/KerasOptimizer.py
pykopt/Strategy.py
pykopt/__init__.py
pykopt/stats.py
pykopt/operator/__init__.py
pykopt/operator/crossover.py
pykopt/operator/selection.py
pykopt/util/__init__.py
pykopt-0.1.6.dist-info/LICENSE.txt
pykopt-0.1.6.dist-info/METADATA
pykopt-0.1.6.dist-info/WHEEL
pykopt-0.1.6.dist-info/top_level.txt
pykopt-0.1.6.dist-info/RECORD
