Metadata-Version: 2.1
Name: pykopt
Version: 0.1.6
Summary: Evolutionary Keras Hyperparameter Optimizer
Home-page: https://github.com/kazimsoylu/pykopt
Author: Kazim SOYLU
Author-email: kazimsoylu@gmail.com
License: UNKNOWN
Platform: UNKNOWN
Classifier: Programming Language :: Python :: 3
Classifier: License :: OSI Approved :: MIT License
Classifier: Operating System :: OS Independent
Requires-Python: >=3.6
